pychampselysees/__init__.py
pychampselysees/pychampselysees.py
pychampselysees-0.1.dist-info/DESCRIPTION.rst
pychampselysees-0.1.dist-info/METADATA
pychampselysees-0.1.dist-info/RECORD
pychampselysees-0.1.dist-info/WHEEL
pychampselysees-0.1.dist-info/metadata.json
pychampselysees-0.1.dist-info/top_level.txt
