Metadata-Version: 2.0
Name: pychampselysees
Version: 0.1
Summary: many python functions for general purpose
Home-page: https://github.com/ribamar-santarosa/pychampselysees
Author: Ribamar Santarosa
Author-email: ribamar@gmail.com
License: UNKNOWN
Download-URL: https://github.com/ribamar-santarosa/pychampselysees/archive/0.1.tar.gz
Keywords: testing,example
Platform: UNKNOWN
